menli/MENLI.py
menli/__init__.py
menli/bart_score.py
menli/metric_utils.py
menli/moverscore_re.py
menli-1.0.1.dist-info/LICENSE
menli-1.0.1.dist-info/METADATA
menli-1.0.1.dist-info/WHEEL
menli-1.0.1.dist-info/top_level.txt
menli-1.0.1.dist-info/RECORD
