Metadata-Version: 2.1
Name: menli
Version: 1.0.1
Summary: MENLI metrics v1
Home-page: https://github.com/cyr19/MENLI
Author: cyr
License-File: LICENSE
Requires-Dist: pandas
Requires-Dist: scipy
Requires-Dist: torch ==1.12.0
Requires-Dist: transformers ==4.17.0
Requires-Dist: bert-score ==0.3.11
Requires-Dist: pyemd
Requires-Dist: pytorch-pretrained-bert
Requires-Dist: mosestokenizer
